git_secrets/__init__.py
git_secrets/cli/__init__.py
git_secrets/cli/cli_library.py
git_secrets/cli/install.py
git_secrets/cli/main.py
git_secrets/cli/scan.py
git_secrets/secrets/__init__.py
git_secrets/secrets/git.py
git_secrets/secrets/install.py
git_secrets/secrets/scan.py
git_secrets/secrets/secrets.py
tests/secrets/__init__.py
tests/secrets/git_test.py
tests/secrets/scan_test.py
tests/secrets/secrets_test.py
qpp_git_secrets-1.1.1.dist-info/LICENSE
qpp_git_secrets-1.1.1.dist-info/METADATA
qpp_git_secrets-1.1.1.dist-info/WHEEL
qpp_git_secrets-1.1.1.dist-info/entry_points.txt
qpp_git_secrets-1.1.1.dist-info/top_level.txt
qpp_git_secrets-1.1.1.dist-info/RECORD
