Metadata-Version: 2.1
Name: qpp-git-secrets
Version: 1.1.1
Summary: Git without secrets
Home-page: https://github.com/halprin/git-secrets
Author: halprin
Author-email: me@halprin.io
License: UNKNOWN
Platform: UNKNOWN
Classifier: Programming Language :: Python :: 3
Classifier: License :: OSI Approved :: GNU General Public License v3 (GPLv3)
Classifier: Operating System :: OS Independent
Requires-Dist: click (==7.0)
Requires-Dist: unidiff (==0.5.5)
